pipscan/__init__.py
pipscan/multi_scan.py
pipscan/single_scan.py
pipscan-1.1.dist-info/LICENSE
pipscan-1.1.dist-info/METADATA
pipscan-1.1.dist-info/WHEEL
pipscan-1.1.dist-info/top_level.txt
pipscan-1.1.dist-info/RECORD
