Metadata-Version: 2.1
Name: pipscan
Version: 1.1
Summary: A Python Library used for network port scanning. Choose between single scanning and multi scanning.
Home-page: https://github.com/YBDeve/PipScan
Author: YB
License: MIT
Classifier: Programming Language :: Python :: 3
Classifier: License :: OSI Approved :: MIT License
Classifier: Operating System :: OS Independent
License-File: LICENSE
